AUTHORS.rst
CONTRIBUTING.rst
HISTORY.rst
LICENSE
MANIFEST.in
README.rst
setup.cfg
setup.py
clarify_python/__init__.py
clarify_python/clarify.py
clarify_python/clarify_export.py
clarify_python/constants.py
clarify_python/helper.py
clarify_python.egg-info/PKG-INFO
clarify_python.egg-info/SOURCES.txt
clarify_python.egg-info/dependency_links.txt
clarify_python.egg-info/entry_points.txt
clarify_python.egg-info/not-zip-safe
clarify_python.egg-info/requires.txt
clarify_python.egg-info/top_level.txt
tests/__init__.py
tests/test_client.py
tests/data/bundle.json
tests/data/bundle_embedded.json
tests/data/bundle_ref.json
tests/data/bundles_1.json
tests/data/insight_classification.json
tests/data/insight_pending.json
tests/data/insights.json
tests/data/metadata.json
tests/data/tracks.json