Metadata-Version: 1.1
Name: clarify-python
Version: 3.1.1
Summary: The Clarify Python Helper Library wraps the entire Clarify API in a Python 3.x / 2.7 Client class.
Home-page: https://github.com/Clarify/clarify_python
Author: Paul Murphy
Author-email: paul@clarify.io
License: MIT
Keywords: clarify_python clarify
Platform: UNKNOWN
Classifier: Development Status :: 5 - Production/Stable
Classifier: Intended Audience :: Developers
Classifier: License :: OSI Approved :: MIT License
Classifier: Natural Language :: English
Classifier: Programming Language :: Python :: 3
